cpforager/__init__.py
cpforager/checks.py
cpforager/constants.py
cpforager/diagnostic.py
cpforager/misc.py
cpforager/parameters.py
cpforager/processing.py
cpforager/utils.py
cpforager/axy/__init__.py
cpforager/axy/axy.py
cpforager/axy/diagnostic.py
cpforager/axy/display.py
cpforager/axy/interpolation.py
cpforager/axy_collection/__init__.py
cpforager/axy_collection/axy_collection.py
cpforager/axy_collection/diagnostic.py
cpforager/axy_collection/display.py
cpforager/gps/__init__.py
cpforager/gps/diagnostic.py
cpforager/gps/display.py
cpforager/gps/gps.py
cpforager/gps/interpolation.py
cpforager/gps_collection/diagnostic.py
cpforager/gps_collection/display.py
cpforager/gps_collection/gps_collection.py
cpforager/gps_collection/stdb.py
cpforager/gps_tdr/__init__.py
cpforager/gps_tdr/diagnostic.py
cpforager/gps_tdr/display.py
cpforager/gps_tdr/gps_tdr.py
cpforager/gps_tdr/interpolation.py
cpforager/gps_tdr_collection/__init__.py
cpforager/gps_tdr_collection/diagnostic.py
cpforager/gps_tdr_collection/display.py
cpforager/gps_tdr_collection/gps_tdr_collection.py
cpforager/tdr/__init__.py
cpforager/tdr/diagnostic.py
cpforager/tdr/display.py
cpforager/tdr/tdr.py
cpforager/tdr_collection/__init__.py
cpforager/tdr_collection/diagnostic.py
cpforager/tdr_collection/display.py
cpforager/tdr_collection/tdr_collection.py
cpforager-1.2.0.dist-info/METADATA
cpforager-1.2.0.dist-info/WHEEL
cpforager-1.2.0.dist-info/licenses/LICENSE
cpforager-1.2.0.dist-info/RECORD
