Metadata-Version: 2.4
Name: cpforager
Version: 1.2.0
Summary: Python package to handle data gathered from biologgers (GPS, TDR, AXY) attached to central-place foraging seabirds. The idea is to make movement ecology data a bit easier to process.
Project-URL: Homepage, https://github.com/AdrienBrunel/cpforager
Project-URL: Repository, https://github.com/AdrienBrunel/cpforager
Project-URL: Documentation, https://adrienbrunel.github.io/cpforager/
Project-URL: Issues, https://github.com/AdrienBrunel/cpforager/issues
Author-email: Adrien Brunel <adrien.brunel.pro@protonmail.com>
Maintainer-email: Adrien Brunel <adrien.brunel.pro@protonmail.com>
License-Expression: AGPL-3.0
License-File: LICENSE
Keywords: accelerometer,biologging,central-place,ecology,foraging,gps,movement,movement-ecology,seabird,tdr,telemetry
Classifier: Intended Audience :: Science/Research
Classifier: License :: OSI Approved :: GNU Affero General Public License v3
Classifier: Natural Language :: English
Classifier: Operating System :: OS Independent
Classifier: Programming Language :: Python :: 3
Classifier: Programming Language :: Python :: 3.11
Classifier: Programming Language :: Python :: 3.12
Classifier: Programming Language :: Python :: 3.13
Classifier: Topic :: Scientific/Engineering
Requires-Python: >=3.11
Requires-Dist: branca>=0.8.1
Requires-Dist: cartopy>=0.24.0
Requires-Dist: folium>=0.19.5
Requires-Dist: matplotlib>=3.10.3
Requires-Dist: numpy>=2.2.5
Requires-Dist: pandas>=2.2.3
Requires-Dist: pytz>=2025.2
Requires-Dist: scipy>=1.16.1
Requires-Dist: suntime>=1.3.2
